RTL/ALU.v
`timescale 1ns / 1ps

module ALU(
    input clk,
    input rst,
    input [15:0] A,
    input [15:0] B,
    input [3:0] opcode,
    input valid_in,

    output reg [15:0] result,
    output reg zero,
    output reg carry,
    output reg overflow,
    output reg negative,
    output reg valid_out
);

    // =========================================
    // Stage 1 Pipeline Registers
    // =========================================
    reg [15:0] A_reg;
    reg [15:0] B_reg;
    reg [3:0] opcode_reg;
    reg valid_stage1;

    // =========================================
    // ALU Internal Signals
    // =========================================
    reg [15:0] alu_result;
    reg alu_zero;
    reg alu_carry;
    reg alu_overflow;
    reg alu_negative;

    // =========================================
    // Stage 2 Pipeline Registers
    // =========================================
    reg [15:0] result_reg;
    reg zero_reg;
    reg carry_reg;
    reg overflow_reg;
    reg negative_reg;
    reg valid_stage2;

    // =========================================
    // Stage 1 Input Register
    // =========================================
    always @(posedge clk)
    begin
        if(rst)
        begin
            A_reg <= 16'd0;
            B_reg <= 16'd0;
            opcode_reg <= 4'd0;
            valid_stage1 <= 1'b0;
        end
        else
        begin
            A_reg <= A;
            B_reg <= B;
            opcode_reg <= opcode;
            valid_stage1 <= valid_in;
        end
    end

    // =========================================
    // Combinational ALU Logic
    // =========================================
    always @(*)
    begin

        // Default Values
        alu_result = 16'd0;
        alu_zero = 1'b0;
        alu_carry = 1'b0;
        alu_overflow = 1'b0;
        alu_negative = 1'b0;

        case(opcode_reg)

            // ADD
            4'd0:
            begin
                {alu_carry, alu_result} = A_reg + B_reg;

                alu_overflow =
                (A_reg[15] == B_reg[15]) &&
                (A_reg[15] != alu_result[15]);
            end

            // SUB
            4'd1:
            begin
                {alu_carry, alu_result} = A_reg - B_reg;

                alu_overflow =
                (A_reg[15] != B_reg[15]) &&
                (A_reg[15] != alu_result[15]);
            end

            // MUL
            4'd2:
            begin
                alu_result = A_reg * B_reg;
                alu_overflow = 1'b0;
            end

            // DIV
            4'd3:
            begin
                if(B_reg != 16'd0)
                    alu_result = A_reg / B_reg;
                else
                    alu_result = 16'd0;

                alu_overflow = 1'b0;
            end

            // AND
            4'd4:
            begin
                alu_result = A_reg & B_reg;
                alu_overflow = 1'b0;
            end

            // OR
            4'd5:
            begin
                alu_result = A_reg | B_reg;
                alu_overflow = 1'b0;
            end

            // XOR
            4'd6:
            begin
                alu_result = A_reg ^ B_reg;
                alu_overflow = 1'b0;
            end

            // NOT
            4'd7:
            begin
                alu_result = ~A_reg;
                alu_overflow = 1'b0;
            end

            // SHIFT LEFT
            4'd8:
            begin
                alu_result = A_reg << 1;
                alu_overflow = 1'b0;
            end

            // SHIFT RIGHT
            4'd9:
            begin
                alu_result = A_reg >> 1;
                alu_overflow = 1'b0;
            end

            // COMPARE EQUAL
            4'd10:
            begin
                alu_result = (A_reg == B_reg);
                alu_overflow = 1'b0;
            end

            // COMPARE GREATER
            4'd11:
            begin
                alu_result = (A_reg > B_reg);
                alu_overflow = 1'b0;
            end

            default:
            begin
                alu_result = 16'd0;
                alu_overflow = 1'b0;
            end

        endcase

        // Common Flag Logic
        alu_zero = (alu_result == 16'd0);
        alu_negative = alu_result[15];

    end

    // =========================================
    // Stage 2 Output Register
    // =========================================
    always @(posedge clk)
    begin

        if(rst)
        begin
            result_reg <= 16'd0;
            zero_reg <= 1'b0;
            carry_reg <= 1'b0;
            overflow_reg <= 1'b0;
            negative_reg <= 1'b0;
            valid_stage2 <= 1'b0;
        end

        else
        begin
            result_reg <= alu_result;
            zero_reg <= alu_zero;
            carry_reg <= alu_carry;
            overflow_reg <= alu_overflow;
            negative_reg <= alu_negative;
            valid_stage2 <= valid_stage1;
        end

    end

    // =========================================
    // Output Assignments
    // =========================================
    always @(*)
    begin
        result = result_reg;
        zero = zero_reg;
        carry = carry_reg;
        overflow = overflow_reg;
        negative = negative_reg;
        valid_out = valid_stage2;
    end

endmodule

RTL/tb_ALU.v
`timescale 1ns / 1ps

module tb_ALU;

    // Inputs
    reg clk;
    reg rst;
    reg [15:0] A;
    reg [15:0] B;
    reg [3:0] opcode;
    reg valid_in;

    // Outputs
    wire [15:0] result;
    wire zero;
    wire carry;
    wire overflow;
    wire negative;
    wire valid_out;

    // DUT
    ALU uut (
        .clk(clk),
        .rst(rst),
        .A(A),
        .B(B),
        .opcode(opcode),
        .valid_in(valid_in),
        .result(result),
        .zero(zero),
        .carry(carry),
        .overflow(overflow),
        .negative(negative),
        .valid_out(valid_out)
    );

    // =========================================
    // Clock Generation
    // =========================================
    always #5 clk = ~clk;

    // =========================================
    // Test Sequence
    // =========================================
    initial
    begin

        // Initial Values
        clk = 0;
        rst = 1;
        A = 0;
        B = 0;
        opcode = 0;
        valid_in = 0;

        // Reset
        #20;
        rst = 0;

        // ADD
        #10;
        A = 16'd20;
        B = 16'd10;
        opcode = 4'd0;
        valid_in = 1;

        // SUB
        #10;
        A = 16'd50;
        B = 16'd15;
        opcode = 4'd1;

        // MUL
        #10;
        A = 16'd12;
        B = 16'd4;
        opcode = 4'd2;

        // DIV
        #10;
        A = 16'd100;
        B = 16'd5;
        opcode = 4'd3;

        // DIVIDE BY ZERO
        #10;
        A = 16'd100;
        B = 16'd0;
        opcode = 4'd3;

        // AND
        #10;
        A = 16'b1010101010101010;
        B = 16'b1111000011110000;
        opcode = 4'd4;

        // OR
        #10;
        opcode = 4'd5;

        // XOR
        #10;
        opcode = 4'd6;

        // NOT
        #10;
        opcode = 4'd7;

        // SHIFT LEFT
        #10;
        A = 16'd8;
        opcode = 4'd8;

        // SHIFT RIGHT
        #10;
        A = 16'd32;
        opcode = 4'd9;

        // COMPARE EQUAL
        #10;
        A = 16'd25;
        B = 16'd25;
        opcode = 4'd10;

        // COMPARE GREATER
        #10;
        A = 16'd40;
        B = 16'd10;
        opcode = 4'd11;

        // OVERFLOW TEST
        #10;
        A = 16'd32760;
        B = 16'd10;
        opcode = 4'd0;

        // Disable valid signal
        #20;
        valid_in = 0;

        // End Simulation
        #100;
        $stop;

    end

    // =========================================
    // Monitor
    // =========================================
    initial
    begin
        $monitor(
        "TIME=%0t | A=%d | B=%d | OPCODE=%d | RESULT=%d | CARRY=%b | OVERFLOW=%b | ZERO=%b | NEGATIVE=%b | VALID=%b",
        $time,
        A,
        B,
        opcode,
        result,
        carry,
        overflow,
        zero,
        negative,
        valid_out
        );
    end

endmodule

Simulation/waveform.vcd
$date
   Tue May 12 23:47:22 2026
$end

$version
  2025.1.0
  $dumpfile ("waveform.vcd") 
$end

$timescale
  1ps
$end

$scope module tb_ALU $end
$var reg 1 ! clk $end
$var reg 1 " rst $end
$var reg 16 # A [15:0] $end
$var reg 16 $ B [15:0] $end
$var reg 4 % opcode [3:0] $end
$var reg 1 & valid_in $end
$var wire 16 ' result [15:0] $end
$var wire 1 ( zero $end
$var wire 1 ) carry $end
$var wire 1 * overflow $end
$var wire 1 + negative $end
$var wire 1 , valid_out $end
$scope module uut $end
$var wire 1 - clk $end
$var wire 1 . rst $end
$var wire 16 / A [15:0] $end
$var wire 16 0 B [15:0] $end
$var wire 4 1 opcode [3:0] $end
$var wire 1 2 valid_in $end
$var reg 16 3 result [15:0] $end
$var reg 1 4 zero $end
$var reg 1 5 carry $end
$var reg 1 6 overflow $end
$var reg 1 7 negative $end
$var reg 1 8 valid_out $end
$var reg 16 9 A_reg [15:0] $end
$var reg 16 : B_reg [15:0] $end
$var reg 4 ; opcode_reg [3:0] $end
$var reg 1 < valid_stage1 $end
$var reg 16 = alu_result [15:0] $end
$var reg 1 > alu_zero $end
$var reg 1 ? alu_carry $end
$var reg 1 @ alu_overflow $end
$var reg 1 A alu_negative $end
$var reg 16 B result_reg [15:0] $end
$var reg 1 C zero_reg $end
$var reg 1 D carry_reg $end
$var reg 1 E overflow_reg $end
$var reg 1 F negative_reg $end
$var reg 1 G valid_stage2 $end
$upscope $end
$upscope $end
$enddefinitions $end

#0
$dumpvars
0!
1"
b0 #
b0 $
b0 %
0&
bx '
x(
x)
x*
x+
x,
0-
1.
b0 /
b0 0
b0 1
02
bx 3
x4
x5
x6
x7
x8
bx 9
bx :
bx ;
x<
bx =
x>
x?
x@
xA
bx B
xC
xD
xE
xF
xG
$end

#5000
1!
b0 '
0(
0)
0*
0+
0,
1-
b0 3
04
05
06
07
08
b0 9
b0 :
b0 ;
0<
b0 =
1>
0?
0@
0A
b0 B
0C
0D
0E
0F
0G

#10000
0!
0-

#15000
1!
1-

#20000
0!
0"
0-
0.

#25000
1!
1(
1-
14
1C

#30000
0!
b10100 #
b1010 $
1&
0-
b10100 /
b1010 0
12

#35000
1!
1-
b10100 9
b1010 :
1<
b11110 =
0>

#40000
0!
b110010 #
b1111 $
b1 %
0-
b110010 /
b1111 0
b1 1

#45000
1!
b11110 '
0(
1,
1-
b11110 3
04
18
b110010 9
b1111 :
b1 ;
b100011 =
b11110 B
0C
1G

#50000
0!
b1100 #
b100 $
b10 %
0-
b1100 /
b100 0
b10 1

#55000
1!
b100011 '
1-
b100011 3
b1100 9
b100 :
b10 ;
b110000 =
b100011 B

#60000
0!
b1100100 #
b101 $
b11 %
0-
b1100100 /
b101 0
b11 1

#65000
1!
b110000 '
1-
b110000 3
b1100100 9
b101 :
b11 ;
b10100 =
b110000 B

#70000
0!
b0 $
0-
b0 0

#75000
1!
b10100 '
1-
b10100 3
b0 :
b0 =
1>
b10100 B

#80000
0!
b1010101010101010 #
b1111000011110000 $
b100 %
0-
b1010101010101010 /
b1111000011110000 0
b100 1

#85000
1!
b0 '
1(
1-
b0 3
14
b1010101010101010 9
b1111000011110000 :
b100 ;
b1010000010100000 =
0>
1A
b0 B
1C

#90000
0!
b101 %
0-
b101 1

#95000
1!
b1010000010100000 '
0(
1+
1-
b1010000010100000 3
04
17
b101 ;
b1111101011111010 =
1A
b1010000010100000 B
0C
1F

#100000
0!
b110 %
0-
b110 1

#105000
1!
b1111101011111010 '
1-
b1111101011111010 3
b110 ;
b101101001011010 =
0A
b1111101011111010 B

#110000
0!
b111 %
0-
b111 1

#115000
1!
b101101001011010 '
0+
1-
b101101001011010 3
07
b111 ;
b101010101010101 =
b101101001011010 B
0F

#120000
0!
b1000 #
b1000 %
0-
b1000 /
b1000 1

#125000
1!
b101010101010101 '
1-
b101010101010101 3
b1000 9
b1000 ;
b10000 =
b101010101010101 B

#130000
0!
b100000 #
b1001 %
0-
b100000 /
b1001 1

#135000
1!
b10000 '
1-
b10000 3
b100000 9
b1001 ;
b10000 =
b10000 B

#140000
0!
b11001 #
b11001 $
b1010 %
0-
b11001 /
b11001 0
b1010 1

#145000
1!
1-
b11001 9
b11001 :
b1010 ;
b1 =

#150000
0!
b101000 #
b1010 $
b1011 %
0-
b101000 /
b1010 0
b1011 1

#155000
1!
b1 '
1-
b1 3
b101000 9
b1010 :
b1011 ;
b1 =
b1 B

#160000
0!
b111111111111000 #
b0 %
0-
b111111111111000 /
b0 1

#165000
1!
1-
b111111111111000 9
b0 ;
b1000000000000010 =
1@
1A

#170000
0!
0-

#175000
1!
b1000000000000010 '
1*
1+
1-
b1000000000000010 3
16
17
b1000000000000010 B
1E
1F

#180000
0!
0&
0-
02

#185000
1!
1-
0<

#190000
0!
0-

#195000
1!
0,
1-
08
0G

